<annotation>
	<folder>all</folder>
	<filename>652.jpg</filename>
	<path>/home/sama/Downloads/data/data/images/all/652.jpg</path>
	<source>
		<database>Unknown</database>
	</source>
	<size>
		<width>800</width>
		<height>600</height>
		<depth>3</depth>
	</size>
	<segmented>0</segmented>
	<object>
		<name>plastic-container</name>
		<pose>Unspecified</pose>
		<truncated>0</truncated>
		<difficult>0</difficult>
		<bndbox>
			<xmin>43</xmin>
			<ymin>61</ymin>
			<xmax>452</xmax>
			<ymax>370</ymax>
		</bndbox>
	</object>
	<object>
		<name>plastic-container</name>
		<pose>Unspecified</pose>
		<truncated>0</truncated>
		<difficult>0</difficult>
		<bndbox>
			<xmin>50</xmin>
			<ymin>264</ymin>
			<xmax>452</xmax>
			<ymax>553</ymax>
		</bndbox>
	</object>
	<object>
		<name>plastic-container</name>
		<pose>Unspecified</pose>
		<truncated>0</truncated>
		<difficult>0</difficult>
		<bndbox>
			<xmin>448</xmin>
			<ymin>307</ymin>
			<xmax>798</xmax>
			<ymax>555</ymax>
		</bndbox>
	</object>
	<object>
		<name>plastic-container</name>
		<pose>Unspecified</pose>
		<truncated>1</truncated>
		<difficult>0</difficult>
		<bndbox>
			<xmin>450</xmin>
			<ymin>169</ymin>
			<xmax>800</xmax>
			<ymax>408</ymax>
		</bndbox>
	</object>
	<object>
		<name>plastic-container</name>
		<pose>Unspecified</pose>
		<truncated>0</truncated>
		<difficult>0</difficult>
		<bndbox>
			<xmin>431</xmin>
			<ymin>2</ymin>
			<xmax>798</xmax>
			<ymax>265</ymax>
		</bndbox>
	</object>
</annotation>
